dnbc4tools/__init__.py
dnbc4tools/dnbc4tools.py
dnbc4tools/atac/__init__.py
dnbc4tools/atac/analysis.py
dnbc4tools/atac/data.py
dnbc4tools/atac/decon.py
dnbc4tools/atac/dnbc4atac.py
dnbc4tools/atac/mkref.py
dnbc4tools/atac/multi.py
dnbc4tools/atac/report.py
dnbc4tools/atac/run.py
dnbc4tools/atac/src/Cluster_Annotation.R
dnbc4tools/atac/src/generate_report.py
dnbc4tools/config/adapter.txt
dnbc4tools/config/oligo_type.json
dnbc4tools/config/oligo_type.txt
dnbc4tools/config/scRNA_beads_darkReaction.json
dnbc4tools/config/scRNA_oligo_R2_noDarkReaction.json
dnbc4tools/config/scRNA_oligo_darkReaction.json
dnbc4tools/config/whitelist_atac.txt.gz
dnbc4tools/config/blacklist/hg19.full.blacklist.bed
dnbc4tools/config/blacklist/hg38.full.blacklist.bed
dnbc4tools/config/blacklist/mm10.full.blacklist.bed
dnbc4tools/config/cellAnno/HCL.ref.csv.gz
dnbc4tools/config/cellAnno/MCA.ref.csv.gz
dnbc4tools/config/scRNAv1HT/scRNA_beads_noDarkReaction_v1.json
dnbc4tools/config/scRNAv1HT/scRNA_oligo_noDarkReaction_v1.json
dnbc4tools/config/scRNAv2HT/scRNA_beads_noDarkReaction_v2.json
dnbc4tools/config/scRNAv2HT/scRNA_oligo_noDarkReaction_v2.json
dnbc4tools/rna/__init__.py
dnbc4tools/rna/analysis.py
dnbc4tools/rna/count.py
dnbc4tools/rna/data.py
dnbc4tools/rna/dnbc4rna.py
dnbc4tools/rna/mkref.py
dnbc4tools/rna/multi.py
dnbc4tools/rna/report.py
dnbc4tools/rna/run.py
dnbc4tools/rna/src/__init__.py
dnbc4tools/rna/src/cellMerge.py
dnbc4tools/rna/src/cell_calling.R
dnbc4tools/rna/src/combinedListOfBeads.py
dnbc4tools/rna/src/generate_report.py
dnbc4tools/rna/src/oligo_filter.py
dnbc4tools/rna/src/saturation.py
dnbc4tools/rna/src/scanpy_cluster.py
dnbc4tools/rna/src/star_anno.py
dnbc4tools/software/Anno
dnbc4tools/software/PISA
dnbc4tools/software/chromap
dnbc4tools/software/parseFq
dnbc4tools/software/scStar
dnbc4tools/software/seqkit
dnbc4tools/software/similarity
dnbc4tools/software/tagAdd
dnbc4tools/software/d2c/bin/CHANGELOG.md
dnbc4tools/software/d2c/bin/README.md
DNBC4_test-2.2.1.dist-info/LICENSE
DNBC4_test-2.2.1.dist-info/METADATA
DNBC4_test-2.2.1.dist-info/WHEEL
DNBC4_test-2.2.1.dist-info/entry_points.txt
DNBC4_test-2.2.1.dist-info/top_level.txt
DNBC4_test-2.2.1.dist-info/RECORD
