Metadata-Version: 2.1
Name: DNBC4-test
Version: 2.2.1
Summary: DNBelab Series Single-Cell analysis workflow
Home-page: https://github.com/lishuangshuang0616/DNBC4tools
Author: lishuangshuang3
Author-email: lishuangshuang3@mgi-tech.com
License: MIT
Platform: Linux
License-File: LICENSE
